whosyouragent/__init__.py
whosyouragent/py.typed
whosyouragent/whosyouragent.py
whosyouragent-2.0.1.dist-info/METADATA
whosyouragent-2.0.1.dist-info/WHEEL
whosyouragent-2.0.1.dist-info/licenses/LICENSE.txt
whosyouragent-2.0.1.dist-info/RECORD
