Metadata-Version: 2.3
Name: whosyouragent
Version: 2.0.1
Summary: Self updating package for generating random user agent strings.
Project-URL: Homepage, https://github.com/matt-manes/whosyouragent
Project-URL: Documentation, https://github.com/matt-manes/whosyouragent/tree/main/docs
Project-URL: Source code, https://github.com/matt-manes/whosyouragent/tree/main/src/whosyouragent
Author: Matt Manes
Keywords: user-agent,useragent,web-scraping,webscraping
Classifier: License :: OSI Approved :: MIT License
Classifier: Operating System :: OS Independent
Classifier: Programming Language :: Python :: 3
Requires-Python: >=3.6
Requires-Dist: beautifulsoup4
Requires-Dist: bs4
Requires-Dist: pytest
Requires-Dist: requests
Requires-Dist: whosyouragent
